cv2PySide6/__init__.py
cv2PySide6/labels.py
cv2PySide6/py.typed
cv2PySide6/util.py
cv2PySide6/version.py
cv2PySide6/videostream.py
cv2PySide6/videoutil.py
cv2PySide6/videowidgets.py
cv2PySide6/data/hello.jpg
cv2PySide6/data/hello.mp4
cv2PySide6/examples/camera/camera.png
cv2PySide6/examples/camera/camera.py
cv2PySide6/examples/videoplayer/videoplayer.png
cv2PySide6/examples/videoplayer/videoplayer.py
cv2PySide6/tests/__init__.py
cv2PySide6/tests/test_labels.py
cv2PySide6/tests/test_videostream.py
cv2PySide6/tests/test_videowidgets.py
cv2PySide6-3.1.0.dist-info/LICENSE.txt
cv2PySide6-3.1.0.dist-info/METADATA
cv2PySide6-3.1.0.dist-info/WHEEL
cv2PySide6-3.1.0.dist-info/top_level.txt
cv2PySide6-3.1.0.dist-info/RECORD
