Metadata-Version: 2.1
Name: cv2PySide6
Version: 3.1.0
Summary: Package for video display with OpenCV-Python and PySide6
Home-page: https://github.com/JSS95/cv2PySide6
Author: Jisoo Song
Author-email: jeesoo9595@snu.ac.kr
Maintainer: Jisoo Song
Maintainer-email: jeesoo9595@snu.ac.kr
License: LGPL
Platform: UNKNOWN
Classifier: Development Status :: 5 - Production/Stable
Classifier: Intended Audience :: Developers
Classifier: Intended Audience :: Science/Research
Classifier: License :: OSI Approved :: GNU Library or Lesser General Public License (LGPL)
Classifier: Operating System :: MacOS :: MacOS X
Classifier: Operating System :: Microsoft
Classifier: Operating System :: Microsoft :: Windows
Classifier: Operating System :: POSIX
Classifier: Operating System :: POSIX :: Linux
Classifier: Programming Language :: Python
Classifier: Programming Language :: Python :: 3
Classifier: Programming Language :: Python :: 3.6
Classifier: Programming Language :: Python :: 3.7
Classifier: Programming Language :: Python :: 3.8
Classifier: Programming Language :: Python :: 3.9
Classifier: Programming Language :: Python :: 3.10
Classifier: Topic :: Multimedia :: Graphics
Classifier: Topic :: Software Development
Classifier: Topic :: Software Development :: Libraries :: Python Modules
Classifier: Topic :: Software Development :: User Interfaces
Classifier: Topic :: Software Development :: Widget Sets
Requires-Python: >=3.6
License-File: LICENSE.txt
Requires-Dist: numpy
Requires-Dist: PySide6 (>=6.2)
Requires-Dist: qimage2ndarray (>=1.9.0)
Provides-Extra: doc
Requires-Dist: numpydoc ; extra == 'doc'
Requires-Dist: sphinx ; extra == 'doc'
Requires-Dist: sphinx-rtd-theme ; extra == 'doc'
Provides-Extra: full
Requires-Dist: black ; extra == 'full'
Requires-Dist: opencv-python-headless ; extra == 'full'
Requires-Dist: sphinx-rtd-theme ; extra == 'full'
Requires-Dist: pytest-qt ; extra == 'full'
Requires-Dist: flake8 ; extra == 'full'
Requires-Dist: mypy ; extra == 'full'
Requires-Dist: pytest ; extra == 'full'
Requires-Dist: numpydoc ; extra == 'full'
Requires-Dist: sphinx ; extra == 'full'
Requires-Dist: pytest-xvfb ; extra == 'full'
Provides-Extra: test
Requires-Dist: black ; extra == 'test'
Requires-Dist: flake8 ; extra == 'test'
Requires-Dist: mypy ; extra == 'test'
Requires-Dist: opencv-python-headless ; extra == 'test'
Requires-Dist: pytest ; extra == 'test'
Requires-Dist: pytest-qt ; extra == 'test'
Provides-Extra: test-ci
Requires-Dist: black ; extra == 'test-ci'
Requires-Dist: flake8 ; extra == 'test-ci'
Requires-Dist: mypy ; extra == 'test-ci'
Requires-Dist: opencv-python-headless ; extra == 'test-ci'
Requires-Dist: pytest ; extra == 'test-ci'
Requires-Dist: pytest-qt ; extra == 'test-ci'
Requires-Dist: pytest-xvfb ; extra == 'test-ci'
